pokemon_showdown_replays/Download.py
pokemon_showdown_replays/Replay.py
pokemon_showdown_replays/Upload.py
pokemon_showdown_replays/__init__.py
pokemon_showdown_replays-0.1.1.dist-info/LICENSE
pokemon_showdown_replays-0.1.1.dist-info/METADATA
pokemon_showdown_replays-0.1.1.dist-info/WHEEL
pokemon_showdown_replays-0.1.1.dist-info/RECORD
