Metadata-Version: 2.1
Name: pokemon-showdown-replays
Version: 0.1.1
Summary: A package for generating pokemon showdown replays from pokemon showdown logs
License: MIT
Author: eyalmen
Author-email: dave.eyal@gmail.com
Requires-Python: >=3.10,<4.0
Classifier: License :: OSI Approved :: MIT License
Classifier: Programming Language :: Python :: 3
Classifier: Programming Language :: Python :: 3.10
Classifier: Programming Language :: Python :: 3.11
